<?xml version="1.0" encoding="UTF-8"?>
<ScrollKeeperContentsList>



  <sect categorycode="Applications">
    <title>Aplikace</title>
    <sect categorycode="ApplicationsAmusement">
      <title>Zábava</title>
      </sect>
    <sect categorycode="ApplicationsEducation">
      <title>Vzdělání</title>
      <sect categorycode="ApplicationsEducationArts">
        <title>Umění</title>
        </sect>
      <sect categorycode="ApplicationsEducationComputer Science">
        <title>Informatika</title>
        </sect>
      <sect categorycode="ApplicationsEducationEnglish">
        <title>Angličtina</title>
        </sect>
      <sect categorycode="ApplicationsEducationLanguage">
        <title>Jazyk</title>
        </sect>
      <sect categorycode="ApplicationsEducationMaths">
        <title>Matematika</title>
        </sect>
      <sect categorycode="ApplicationsEducationMusic">
        <title>Hudba</title>
        </sect>
      <sect categorycode="ApplicationsEducationScience">
        <title>Věda</title>
        </sect>
      <sect categorycode="ApplicationsEducationTechnology">
        <title>Technologie</title>
        </sect>
      <sect categorycode="ApplicationsEducationTesting">
        <title>Testování</title>
        </sect>
      <sect categorycode="ApplicationsEducationOther">
        <title>Ostatní</title>
        </sect>
    </sect>
    <sect categorycode="ApplicationsGames">
      <title>Hry</title>
      <sect categorycode="ApplicationsGamesArcade">
        <title>Arkády</title>
        </sect>
      <sect categorycode="ApplicationsGamesBoard">
        <title>Deskové</title>
        </sect>
      <sect categorycode="ApplicationsGamesFirst Person Shooters">
        <title>Střílečky v první osobě</title>
        </sect>
      <sect categorycode="ApplicationsGamesPuzzles">
        <title>Hádanky</title>
        </sect>
      <sect categorycode="ApplicationsGamesFighting">
        <title>Bojové</title>
        </sect>
      <sect categorycode="ApplicationsGamesRole-Playing">
        <title>Hry na hrdiny</title>
        </sect>
      <sect categorycode="ApplicationsGamesSimulation">
        <title>Simlace</title>
        </sect>
      <sect categorycode="ApplicationsGamesStrategy">
        <title>Strategie</title>
        </sect>
      <sect categorycode="ApplicationsGamesOther">
        <title>Ostatní</title>
        </sect>
    </sect>
    <sect categorycode="ApplicationsInternet">
      <title>Internet</title>
      <sect categorycode="ApplicationsInternetChat">
        <title>Chat</title>
        </sect>
      <sect categorycode="ApplicationsInternetEmail">
        <title>E-mail</title>
        </sect>
      <sect categorycode="ApplicationsInternetFax">
        <title>Fax</title>
        </sect>
      <sect categorycode="ApplicationsInternetFile Sharing">
        <title>Sdílení souborů</title>
        </sect>
      <sect categorycode="ApplicationsInternetFTP">
        <title>FTP</title>
        </sect>
      <sect categorycode="ApplicationsInternetInternet Phone">
        <title>Internetový telefon</title>
        </sect>
      <sect categorycode="ApplicationsInternetMessaging">
        <title>Posílání zpráv</title>
        </sect>
      <sect categorycode="ApplicationsInternetNews">
        <title>News</title>
        </sect>
      <sect categorycode="ApplicationsInternetVideo Conferencing">
        <title>Videokonference</title>
        </sect>
      <sect categorycode="ApplicationsInternetWeb">
        <title>WWW</title>
        </sect>
      <sect categorycode="ApplicationsInternetOther">
        <title>Ostatní</title>
        </sect>
    </sect>
    <sect categorycode="ApplicationsMultimedia">
      <title>Multimédia</title>
      <sect categorycode="ApplicationsMultimediaGraphics">
        <title>Grafika</title>
        <sect categorycode="ApplicationsMultimediaGraphics3D Modelling">
          <title>3D modelování</title>
          </sect>
        <sect categorycode="ApplicationsMultimediaGraphics3D Rendering">
          <title>3D renderování</title>
          </sect>
        <sect categorycode="ApplicationsMultimediaGraphicsCAD">
          <title>CAD</title>
          </sect>
        <sect categorycode="ApplicationsMultimediaGraphicsCapture">
          <title>Zachycení</title>
          </sect>
        <sect categorycode="ApplicationsMultimediaGraphicsConversion">
          <title>Konverze</title>
          </sect>
        <sect categorycode="ApplicationsMultimediaGraphicsDrawing">
          <title>Kreslení</title>
          </sect>
        <sect categorycode="ApplicationsMultimediaGraphicsEditing">
          <title>Úpravy</title>
          </sect>
        <sect categorycode="ApplicationsMultimediaGraphicsViewing">
          <title>Zpobrazování</title>
          </sect>
        <sect categorycode="ApplicationsMultimediaGraphicsOther">
          <title>Ostatní</title>
          </sect>
      </sect>
      <sect categorycode="ApplicationsMultimediaSound">
        <title>Zvuk</title>
        <sect categorycode="ApplicationsMultimediaSoundAnalysis">
          <title>Analýza</title>
          </sect>
        <sect categorycode="ApplicationsMultimediaSoundCD Mastering">
          <title>Vytváření CD</title>
          </sect>
        <sect categorycode="ApplicationsMultimediaSoundConversion">
          <title>Konverze</title>
          </sect>
        <sect categorycode="ApplicationsMultimediaSoundEditing">
          <title>Úpravy</title>
          </sect>
        <sect categorycode="ApplicationsMultimediaSoundMIDI">
          <title>MIDI</title>
          </sect>
        <sect categorycode="ApplicationsMultimediaSoundMixers">
          <title>Mixéry</title>
          </sect>
        <sect categorycode="ApplicationsMultimediaSoundPlayers">
          <title>Přehrávače</title>
          </sect>
        <sect categorycode="ApplicationsMultimediaSoundRecording">
          <title>Záznam</title>
          </sect>
        <sect categorycode="ApplicationsMultimediaSoundSpeech">
          <title>Řeč</title>
          </sect>
        <sect categorycode="ApplicationsMultimediaSoundOther">
          <title>Ostatní</title>
          </sect>
      </sect>
      <sect categorycode="ApplicationsMultimediaVideo">
        <title>Video</title>
        <sect categorycode="ApplicationsMultimediaVideoCapture">
          <title>Zachycení</title>
          </sect>
        <sect categorycode="ApplicationsMultimediaVideoConversion">
          <title>Konverze</title>
          </sect>
        <sect categorycode="ApplicationsMultimediaVideoDisplay">
          <title>Zobrazení</title>
          </sect>
        <sect categorycode="ApplicationsMultimediaVideoEditing">
          <title>Úpravy</title>
          </sect>
        <sect categorycode="ApplicationsMultimediaVideoOther">
          <title>Ostatní</title>
          </sect>
      </sect>
      <sect categorycode="ApplicationsMultimediaOther">
        <title>Ostatní</title>
        </sect>
    </sect>
    <sect categorycode="ApplicationsOffice">
      <title>Kancelář</title>
      <sect categorycode="ApplicationsOfficeCalendar">
        <title>Kalendář</title>
        </sect>
      <sect categorycode="ApplicationsOfficeData Processing">
        <title>Zpracování dat</title>
        </sect>
      <sect categorycode="ApplicationsOfficeDatabase">
        <title>Databáze</title>
        </sect>
      <sect categorycode="ApplicationsOfficeEmail">
        <title>E-mail</title>
        </sect>
      <sect categorycode="ApplicationsOfficeFinancial">
        <title>Finanční</title>
        </sect>
      <sect categorycode="ApplicationsOfficePIM">
        <title>PIM</title>
        </sect>
      <sect categorycode="ApplicationsOfficePlotting">
        <title>Kreslení grafů</title>
        </sect>
      <sect categorycode="ApplicationsOfficePresentation">
        <title>Prezentace</title>
        </sect>
      <sect categorycode="ApplicationsOfficePublishing">
        <title>Publikování</title>
        <sect categorycode="ApplicationsOfficePublishingWeb Publishing">
          <title>Publikování na WWW</title>
          </sect>
      </sect>
      <sect categorycode="ApplicationsOfficeWord Processing">
        <title>Zpracování textu</title>
        </sect>
      <sect categorycode="ApplicationsOfficeOther">
        <title>Ostatní</title>
        </sect>
    </sect>
    <sect categorycode="ApplicationsScientific">
      <title>Vědecký</title>
      <sect categorycode="ApplicationsScientificAstronomy">
        <title>Astronomie</title>
        </sect>
      <sect categorycode="ApplicationsScientificAstrophysics">
        <title>Astrofyzika</title>
        </sect>
      <sect categorycode="ApplicationsScientificBiology">
        <title>Biologie</title>
        </sect>
      <sect categorycode="ApplicationsScientificChemistry">
        <title>Chemie</title>
        </sect>
      <sect categorycode="ApplicationsScientificEDA">
        <title>EDA</title>
        </sect>
      <sect categorycode="ApplicationsScientificGenetics">
        <title>Genetika</title>
        </sect>
      <sect categorycode="ApplicationsScientificMath">
        <title>Matematika</title>
        </sect>
      <sect categorycode="ApplicationsScientificPhysics">
        <title>Fyzika</title>
        </sect>
      <sect categorycode="ApplicationsScientificVisualisation">
        <title>Vizualizace</title>
        </sect>
      <sect categorycode="ApplicationsScientificOther">
        <title>Ostatní</title>
        </sect>
    </sect>
    <sect categorycode="ApplicationsSecurity">
      <title>Bezpečnost</title>
      <sect categorycode="ApplicationsSecurityCryptography">
        <title>Kryptografie</title>
        </sect>
      <sect categorycode="ApplicationsSecurityOther">
        <title>Ostatní</title>
        </sect>
    </sect>
    <sect categorycode="ApplicationsText Editors">
      <title>Textové editory</title>
      <sect categorycode="ApplicationsText EditorsCLI">
        <title>CLI</title>
        </sect>
      <sect categorycode="ApplicationsText EditorsGUI">
        <title>GUI</title>
        </sect>
      <sect categorycode="ApplicationsText EditorsOther">
        <title>Ostatní</title>
        </sect>
    </sect>
    <sect categorycode="ApplicationsUtilities">
      <title>Nástroje</title>
      <sect categorycode="ApplicationsUtilitiesArchiving">
        <title>Archivování</title>
        </sect>
      <sect categorycode="ApplicationsUtilitiesCalculating">
        <title>Výpočty</title>
        </sect>
      <sect categorycode="ApplicationsUtilitiesClocks">
        <title>Hodiny</title>
        </sect>
      <sect categorycode="ApplicationsUtilitiesCompression">
        <title>Komprese</title>
        </sect>
      <sect categorycode="ApplicationsUtilitiesFile Utilities">
        <title>Souborové nástroje</title>
        </sect>
      <sect categorycode="ApplicationsUtilitiesMonitors">
        <title>Monitory</title>
        </sect>
      <sect categorycode="ApplicationsUtilitiesPrinting">
        <title>Tisk</title>
        </sect>
      <sect categorycode="ApplicationsUtilitiesTerminals">
        <title>Terminály</title>
        </sect>
      <sect categorycode="ApplicationsUtilitiesText Utilities">
        <title>Textové nástroje</title>
        </sect>
      <sect categorycode="ApplicationsUtilitiesOther">
        <title>Ostatní</title>
        </sect>
    </sect>
    <sect categorycode="ApplicationsX">
      <title>X</title>
      <sect categorycode="ApplicationsXConfiguration">
        <title>Konfigurace</title>
        </sect>
      <sect categorycode="ApplicationsXFonts">
        <title>Písma</title>
        </sect>
      <sect categorycode="ApplicationsXLogin Managers">
        <title>Správci přihlášení</title>
        </sect>
      <sect categorycode="ApplicationsXScreensavers">
        <title>Šetřiče obrazovky</title>
        </sect>
      <sect categorycode="ApplicationsXWindow Managers">
        <title>Manažeři oken</title>
        </sect>
      <sect categorycode="ApplicationsXOther">
        <title>Ostatní</title>
        </sect>
    </sect>
  </sect>

  <sect categorycode="CDE">
    <title>CDE</title>
    </sect>

  <sect categorycode="Development">
    <title>Vývoj</title>
    <sect categorycode="DevelopmentDatabases">
      <title>Databáze</title>
      </sect>
    <sect categorycode="DevelopmentDevelopment Tools">
      <title>Vývojové nástroje</title>
      <sect categorycode="DevelopmentDevelopment ToolsBuild Tools">
        <title>Nástroje pro překlad</title>
        </sect>
      <sect categorycode="DevelopmentDevelopment ToolsCode Generators">
        <title>Generátory kódu</title>
        </sect>
      <sect categorycode="DevelopmentDevelopment ToolsConfiguration">
        <title>Konfigurace</title>
        </sect>
      <sect categorycode="DevelopmentDevelopment ToolsDebuggers">
        <title>Debuggery</title>
        </sect>
      <sect categorycode="DevelopmentDevelopment ToolsIDEs">
        <title>IDE</title>
        </sect>
      <sect categorycode="DevelopmentDevelopment ToolsPackaging">
        <title>Balení</title>
        </sect>
      <sect categorycode="DevelopmentDevelopment ToolsProfiling">
        <title>Profilování</title>
        </sect>
      <sect categorycode="DevelopmentDevelopment ToolsRAD">
        <title>RAD</title>
        </sect>
      <sect categorycode="DevelopmentDevelopment ToolsVersion Control">
        <title>Správa verzí</title>
        </sect>
      <sect categorycode="DevelopmentDevelopment ToolsOther">
        <title>Ostatní</title>
        </sect>
    </sect>
    <sect categorycode="DevelopmentEnvironments">
      <title>Prostředí</title>
      <sect categorycode="DevelopmentEnvironmentsADA">
        <title>ADA</title>
        </sect>
      <sect categorycode="DevelopmentEnvironmentsC">
        <title>C</title>
        </sect>
      <sect categorycode="DevelopmentEnvironmentsC++">
        <title>C++</title>
        </sect>
      <sect categorycode="DevelopmentEnvironmentsGNOME">
        <title>GNOME</title>
        </sect>
      <sect categorycode="DevelopmentEnvironmentsGTK+">
        <title>GTK+</title>
        </sect>
      <sect categorycode="DevelopmentEnvironmentsgtk++">
        <title>gtk++</title>
        </sect>
      <sect categorycode="DevelopmentEnvironmentsJava">
        <title>Java</title>
        </sect>
      <sect categorycode="DevelopmentEnvironmentsKDE">
        <title>KDE</title>
        </sect>
      <sect categorycode="DevelopmentEnvironmentsPerl">
        <title>Perl</title>
        </sect>
      <sect categorycode="DevelopmentEnvironmentsPython">
        <title>Python</title>
        </sect>
      <sect categorycode="DevelopmentEnvironmentsQt">
        <title>Qt</title>
        </sect>
      <sect categorycode="DevelopmentEnvironmentsTcl/Tk">
        <title>Tcl/Tk</title>
        </sect>
      <sect categorycode="DevelopmentEnvironmentsWebML">
        <title>WebML</title>
        </sect>
      <sect categorycode="DevelopmentEnvironmentsOther">
        <title>Ostatní</title>
        </sect>
    </sect>
    <sect categorycode="DevelopmentKernels">
      <title>Jádra</title>
      <sect categorycode="DevelopmentKernelsFreeBSD">
        <title>FreeBSD</title>
        </sect>
      <sect categorycode="DevelopmentKernelsLinux">
        <title>Linuc</title>
        </sect>
      <sect categorycode="DevelopmentKernelsNetBSD">
        <title>NetBSD</title>
        </sect>
      <sect categorycode="DevelopmentKernelsOther">
        <title>Ostatní</title>
        </sect>
    </sect>
    <sect categorycode="DevelopmentLibraries">
      <title>Knihovny</title>
      </sect>
    <sect categorycode="DevelopmentSystem Calls">
      <title>Systémová volání</title>
      </sect>
    <sect categorycode="DevelopmentOther">
      <title>Ostatní</title>
      </sect>
  </sect>
  <sect categorycode="General">
    <title>Obecné</title>
    <sect categorycode="GeneralLicenses">
      <title>Licence</title>
      </sect>
    <sect categorycode="GeneralLinux">
      <title>Linuc</title>
      <sect categorycode="GeneralLinuxDistributions">
        <title>Distribuce</title>
        <sect categorycode="GeneralLinuxDistributionsCaldera">
          <title>Caldera</title>
          </sect>
        <sect categorycode="GeneralLinuxDistributionsDebian">
          <title>Debian</title>
          </sect>
        <sect categorycode="GeneralLinuxDistributionsMandrake">
          <title>Mandrake</title>
          </sect>
        <sect categorycode="GeneralLinuxDistributionsRed Flag">
          <title>Red Flag</title>
          </sect>
        <sect categorycode="GeneralLinuxDistributionsRed Hat">
          <title>Red Hat</title>
          </sect>
        <sect categorycode="GeneralLinuxDistributionsSlackware">
          <title>Slackware</title>
          </sect>
        <sect categorycode="GeneralLinuxDistributionsSuSE">
          <title>SuSE</title>
          </sect>
        <sect categorycode="GeneralLinuxDistributionsOther">
          <title>Ostatní</title>
          </sect>
      </sect>
      <sect categorycode="GeneralLinuxGeneral">
        <title>Obecné</title>
        </sect>
      <sect categorycode="GeneralLinuxOther">
        <title>Ostatní</title>
        </sect>
    </sect>
    <sect categorycode="GeneralOther">
      <title>Ostatní</title>
      </sect>
  </sect>

  <sect categorycode="GNOME">
    <title>GNOME</title>
    <sect categorycode="GNOMEAccessibility">
      <title>Zpřístupnění</title>
      </sect>
    <sect categorycode="GNOMECore Desktop">
      <title>Základní prostředí pracovní plochy</title>
      </sect>
    <sect categorycode="GNOMEDesktop">
      <title>Pracovní plocha</title>
      <sect categorycode="GNOMEDesktopUser Guides">
        <title>Uživatelské příručky</title>
        </sect>
    </sect>
    <sect categorycode="GNOMEApplets">
      <title>Applety</title>
      <sect categorycode="GNOMEAppletsAccessories">
        <title>Příslušenství</title>
        </sect>
      <sect categorycode="GNOMEAppletsAmusement">
        <title>Zábava</title>
        </sect>
      <sect categorycode="GNOMEAppletsClock">
        <title>Hodiny</title>
        </sect>
      <sect categorycode="GNOMEAppletsInternet">
        <title>Internet</title>
        </sect>
      <sect categorycode="GNOMEAppletsMonitors">
        <title>Monitory</title>
        </sect>
      <sect categorycode="GNOMEAppletsMultimedia">
        <title>Multimédia</title>
        </sect>
      <sect categorycode="GNOMEAppletsNetwork">
        <title>Síť</title>
        </sect>
      <sect categorycode="GNOMEAppletsUtility">
        <title>Nástroj</title>
        </sect>
    </sect>
    <sect categorycode="GNOMEApplications">
      <title>Aplikace</title>
      <sect categorycode="GNOMEApplicationsAccessories">
        <title>Příslušenství</title>
        </sect>
      <sect categorycode="GNOMEApplicationsDesktop Preferences">
        <title>Nastavení pracovní plochy</title>
        </sect>
      <sect categorycode="GNOMEApplicationsGames">
        <title>Hry</title>
        </sect>
      <sect categorycode="GNOMEApplicationsGraphics">
        <title>Grafika</title>
        </sect>
      <sect categorycode="GNOMEApplicationsInternet">
        <title>Internet</title>
        </sect>
      <sect categorycode="GNOMEApplicationsOffice">
        <title>Kancelář</title>
        </sect>
      <sect categorycode="GNOMEApplicationsProgramming">
        <title>Programování</title>
        </sect>
      <sect categorycode="GNOMEApplicationsSound and Video">
        <title>Zvuk a video</title>
        </sect>
      <sect categorycode="GNOMEApplicationsSystem Tools">
        <title>Systémové nástroje</title>
        </sect>
    </sect>
    <sect categorycode="GNOMEPreferences">
      <title>Nastavení</title>
      </sect>
    <sect categorycode="GNOMESystem Administration">
      <title>Správa systému</title>
      </sect>
    <sect categorycode="GNOMEUtilities">
      <title>Nástroje</title>
      </sect>
    <sect categorycode="GNOMEDevelopment">
      <title>Vývoj</title>
      <sect categorycode="GNOMEDevelopmentApplications">
        <title>Aplikace</title>
        </sect>
      <sect categorycode="GNOMEDevelopmentIntroductory">
        <title>Úvodní</title>
        </sect>
      <sect categorycode="GNOMEDevelopmentTutorials">
        <title>Úvodní kurzy</title>
        </sect>
      <sect categorycode="GNOMEDevelopmentWhite Papers">
        <title>White Papers</title>
        </sect>
    </sect>
    <sect categorycode="GNOMEGames">
      <title>Hry</title>
      </sect>
    <sect categorycode="GNOMEGraphics">
      <title>Grafika</title>
      </sect>
    <sect categorycode="GNOMEInternet">
      <title>Internet</title>
      </sect>
    <sect categorycode="GNOMEMultimedia">
      <title>Multimédia</title>
      </sect>
    <sect categorycode="GNOMESettings">
      <title>Nastavení</title>
      </sect>
    <sect categorycode="GNOMESystem">
      <title>Systém</title>
      </sect>
    <sect categorycode="GNOMEOther">
      <title>Ostatní</title>
      </sect>
  </sect>

  <sect categorycode="KDE">
    <title>KDE</title>
    <sect categorycode="KDEUtilities">
      <title>Nástroje</title>
      </sect>
    <sect categorycode="KDEApplications">
      <title>Aplikace</title>
      </sect>
    <sect categorycode="KDEGames">
      <title>Hry</title>
      </sect>
    <sect categorycode="KDEGraphics">
      <title>Grafika</title>
      </sect>
    <sect categorycode="KDEInternet">
      <title>Internet</title>
      </sect>
    <sect categorycode="KDEMultimedia">
      <title>Multimédia</title>
      </sect>
    <sect categorycode="KDESettings">
      <title>Nastavení</title>
      </sect>
    <sect categorycode="KDESystem">
      <title>Systém</title>
      </sect>
    <sect categorycode="KDEPrograms">
      <title>Programy</title>
      </sect>
    <sect categorycode="KDEDevelopment">
      <title>Vývoj</title>
      </sect>
    <sect categorycode="KDEOther">
      <title>Ostatní</title>
      </sect>
  </sect>

  <sect categorycode="System">
    <title>Systém</title>
    <sect categorycode="SystemAdministration">
      <title>Administrace</title>
      <sect categorycode="SystemAdministrationBackups">
        <title>Zálohy</title>
        <sect categorycode="SystemAdministrationBackupsLocal">
          <title>Místní</title>
          </sect>
        <sect categorycode="SystemAdministrationBackupsRemote">
          <title>Vzdálený</title>
          </sect>
      </sect>
      <sect categorycode="SystemAdministrationFilesystems">
        <title>Souborové systémy</title>
        </sect>
      <sect categorycode="SystemAdministrationNetworking">
        <title>Sítě</title>
        <sect categorycode="SystemAdministrationNetworkingAppleTalk">
          <title>AppleTalk</title>
          </sect>
        <sect categorycode="SystemAdministrationNetworkingPPP">
          <title>PPP</title>
          </sect>
        <sect categorycode="SystemAdministrationNetworkingSMB">
          <title>SMB</title>
          </sect>
        <sect categorycode="SystemAdministrationNetworkingTCP/IP">
          <title>TCP/IP</title>
          </sect>
        <sect categorycode="SystemAdministrationNetworkingDNS">
          <title>DNS</title>
          </sect>
        <sect categorycode="SystemAdministrationNetworkingOther">
          <title>Ostatní</title>
          </sect>
      </sect>
      <sect categorycode="SystemAdministrationUsers">
        <title>Uživatelé</title>
        </sect>
      <sect categorycode="SystemAdministrationOther">
        <title>Ostatní</title>
        </sect>
    </sect>
    <sect categorycode="SystemConfiguration">
      <title>Konfigurace</title>
      <sect categorycode="SystemConfigurationConfig Files">
        <title>Konfigurační souboru</title>
        </sect>
      <sect categorycode="SystemConfigurationConfiguration Tools">
        <title>Konfigurační nástroje</title>
        </sect>
      <sect categorycode="SystemConfigurationOther">
        <title>Ostatní</title>
        </sect>
    </sect>
    <sect categorycode="SystemHardware">
      <title>Hardware</title>
      <sect categorycode="SystemHardwareProcessor">
        <title>Procesor</title>
        </sect>
      <sect categorycode="SystemHardwareStorage">
        <title>Ukládání</title>
        </sect>
      <sect categorycode="SystemHardwareVideo">
        <title>Video</title>
        </sect>
      <sect categorycode="SystemHardwareInput Devices">
        <title>Vstupní zařízení</title>
        </sect>
      <sect categorycode="SystemHardwareNetworking">
        <title>Sítě</title>
        </sect>
      <sect categorycode="SystemHardwarePCI/ISA/PCMCIA">
        <title>PCI/ISA/PCMCIA</title>
        </sect>
      <sect categorycode="SystemHardwareOther">
        <title>Ostatní</title>
        </sect>
    </sect>
    <sect categorycode="SystemPackage Management">
      <title>Správa balíčků</title>
      </sect>
    <sect categorycode="SystemSecurity">
      <title>Bezpečnost</title>
      <sect categorycode="SystemSecurityFirewall">
        <title>Firewall</title>
        </sect>
      <sect categorycode="SystemSecurityIntrusion Detection">
        <title>Detekce průniku</title>
        </sect>
      <sect categorycode="SystemSecurityVirus">
        <title>Vir</title>
        </sect>
      <sect categorycode="SystemSecurityOther">
        <title>Ostatní</title>
        </sect>
    </sect>
    <sect categorycode="SystemServices">
      <title>Služby</title>
      <sect categorycode="SystemServicesHTTP">
        <title>HTTP</title>
        </sect>
      <sect categorycode="SystemServicesFTP">
        <title>FTP</title>
        </sect>
      <sect categorycode="SystemServicesSMB">
        <title>SMB</title>
        </sect>
      <sect categorycode="SystemServicesSSH">
        <title>SSH</title>
        </sect>
      <sect categorycode="SystemServicesTelnet">
        <title>Telnet</title>
        </sect>
      <sect categorycode="SystemServicesSyslog">
        <title>Syslog</title>
        </sect>
      <sect categorycode="SystemServicesBIND">
        <title>BIND</title>
        </sect>
      <sect categorycode="SystemServicesPrinting">
        <title>Tisk</title>
        </sect>
      <sect categorycode="SystemServicesOther">
        <title>Ostatní</title>
        </sect>
    </sect>
    <sect categorycode="SystemOther">
      <title>Ostatní</title>
      </sect>
  </sect>
</ScrollKeeperContentsList>
